zmz/__init__.py
zmz/__main__.py
zmz/model/__init__.py
zmz/model/resource.py
zmz/model/result.py
zmz/utility/__init__.py
zmz/utility/api.py
zmz/utility/error.py
zmz/utility/helper.py
zmz-1.1.4.dist-info/METADATA
zmz-1.1.4.dist-info/WHEEL
zmz-1.1.4.dist-info/entry_points.txt
zmz-1.1.4.dist-info/top_level.txt
zmz-1.1.4.dist-info/RECORD
