Metadata-Version: 2.1
Name: zmz
Version: 1.1.4
Summary: An CLI tool for fetching episode download links from www.zimuzu.tv.
Home-page: https://github.com/ikarishinjigao/Zimuzu-Spider-Python
Author: ikarishinjigao
Author-email: ikarishinjigao@gmail.com
License: MIT License
Keywords: zmz,zimuzu,yyets
Platform: UNKNOWN
Classifier: Development Status :: 4 - Beta
Classifier: Intended Audience :: Science/Research
Classifier: License :: OSI Approved :: MIT License
Classifier: Natural Language :: English
Classifier: Programming Language :: Python :: 3.7
Classifier: Programming Language :: Python :: 3 :: Only
Requires-Dist: click
Requires-Dist: lxml
Requires-Dist: bs4
Requires-Dist: requests
